correctmatch/__init__.py
correctmatch-1.4.1.dist-info/METADATA
correctmatch-1.4.1.dist-info/WHEEL
correctmatch-1.4.1.dist-info/licenses/LICENSE
correctmatch-1.4.1.dist-info/RECORD
