Metadata-Version: 2.4
Name: correctmatch
Version: 1.4.1
Summary: Python wrapper for the Julia package CorrectMatch.jl
Project-URL: homepage, https://github.com/computationalprivacy/pycorrectmatch
License-File: LICENSE
Requires-Python: >=3.11
Requires-Dist: juliacall>=0.9.0
Requires-Dist: numpy>=2.0
Requires-Dist: pandas>=2.3.0
Provides-Extra: test
Requires-Dist: pytest-cov>=7.0.0; extra == 'test'
Requires-Dist: pytest-lazy-fixtures>=1.4.0; extra == 'test'
Requires-Dist: pytest-xdist>=3.8.0; extra == 'test'
Requires-Dist: pytest>=9.0.2; extra == 'test'
